<?xml version="1.0" encoding="UTF-8"?>
<person key="adrian-ochoa" xml:lang="eng">
    <name>Adrian Ochoa</name>
    <description>Adrián Ochoa was serving as his ward’s high priests group leader when he was called
        as second counselor in the Young Men general presidency. He has also served as a stake
        president, area public affairs director, Area Seventy, and mission president.</description>
    <url>http://www.lds.org/church/leader/adrian-ochoa?lang=eng</url>
    <memberOf>Second Quorum of the Seventy</memberOf>
    <honorificPrefix>Elder</honorificPrefix>
</person>
