<?xml version="1.0" encoding="UTF-8"?>
<person key="j-devn-cornish" xml:lang="eng">
    <name>J. Devn Cornish</name>
    <description>Elder J. Devn Cornish was sustained a member of the Second Quorum of the Seventy of
        The Church of Jesus Christ of Latter-day Saints on April 2, 2011, at age 59. At the time of
        his call, he had been serving as a member of the Sixth Quorum of the Seventy in the North
        America Southeast Area.</description>
    <url>http://www.lds.org/church/leader/j-devn-cornish?lang=eng</url>
    <memberOf>Second Quorum of the Seventy</memberOf>
    <honorificPrefix>Elder</honorificPrefix>
</person>
